datacollector_api_client/__init__.py
datacollector_api_client/client.py
datacollector_api_client/dbutils_proxy.py
datacollector_api_client/py.typed
datacollector_api_client-0.1.4.dist-info/LICENSE
datacollector_api_client-0.1.4.dist-info/WHEEL
datacollector_api_client-0.1.4.dist-info/METADATA
datacollector_api_client-0.1.4.dist-info/RECORD
