Metadata-Version: 2.1
Name: datacollector-api-client
Version: 0.1.4
Summary: Thin client for Azure Monitor DataCollector API.
Home-page: https://github.com/francisco-ltech/datacollector-api-client
License: MIT
Keywords: datacollector,azure,monitor,poetry
Author: Francisco Ruiz A
Author-email: francisco@ltech.io
Requires-Python: >=3.8,<4.0
Classifier: License :: OSI Approved :: MIT License
Classifier: Programming Language :: Python :: 3
Classifier: Programming Language :: Python :: 3.10
Classifier: Programming Language :: Python :: 3.8
Classifier: Programming Language :: Python :: 3.9
Requires-Dist: requests (>=2.28.1,<3.0.0)
Project-URL: Repository, https://github.com/francisco-ltech/datacollector-api-client
